cratepy/__init__.py
cratepy/main.py
cratepy/clustering/__init__.py
cratepy/clustering/citoperations.py
cratepy/clustering/clusteringalgs.py
cratepy/clustering/clusteringdata.py
cratepy/clustering/clusteringphase.py
cratepy/clustering/crve.py
cratepy/clustering/rveelasticdatabase.py
cratepy/clustering/adaptivity/__init__.py
cratepy/clustering/adaptivity/adaptivity_criterion.py
cratepy/clustering/adaptivity/crve_adaptivity.py
cratepy/clustering/solution/__init__.py
cratepy/clustering/solution/dnshomogenization.py
cratepy/clustering/solution/ffthombasicscheme.py
cratepy/ioput/__init__.py
cratepy/ioput/fileoperations.py
cratepy/ioput/info.py
cratepy/ioput/ioutilities.py
cratepy/ioput/packager.py
cratepy/ioput/readinputdata.py
cratepy/ioput/readprocedures.py
cratepy/ioput/incoutputfiles/__init__.py
cratepy/ioput/incoutputfiles/efftanoutput.py
cratepy/ioput/incoutputfiles/homresoutput.py
cratepy/ioput/incoutputfiles/interface.py
cratepy/ioput/incoutputfiles/refmatoutput.py
cratepy/ioput/miscoutputfiles/__init__.py
cratepy/ioput/miscoutputfiles/voxelsoutput.py
cratepy/ioput/miscoutputfiles/vtkoutput.py
cratepy/material/__init__.py
cratepy/material/isotropichardlaw.py
cratepy/material/materialmodeling.py
cratepy/material/materialoperations.py
cratepy/material/models/__init__.py
cratepy/material/models/elastic.py
cratepy/material/models/interface.py
cratepy/material/models/stvenant_kirchhoff.py
cratepy/material/models/von_mises.py
cratepy/online/__init__.py
cratepy/online/crom/__init__.py
cratepy/online/crom/asca.py
cratepy/online/loading/__init__.py
cratepy/online/loading/macloadincrem.py
cratepy/optimization/__init__.py
cratepy/optimization/optimizationfunction.py
cratepy/optimization/optimizer.py
cratepy/tensor/__init__.py
cratepy/tensor/matrixoperations.py
cratepy/tensor/tensoroperations.py
cratepy-1.0.6.dist-info/METADATA
cratepy-1.0.6.dist-info/WHEEL
cratepy-1.0.6.dist-info/top_level.txt
cratepy-1.0.6.dist-info/RECORD
