Metadata-Version: 2.4
Name: cratepy
Version: 1.0.6
Summary: CRATE: Clustering-based Nonlinear Analysis of Materials
Home-page: https://github.com/bessagroup/CRATE
Author: Bernardo Ferreira
Author-email: bernardoferreiraacc@gmail.com
License: BSD-3-Clause License
Keywords: simulation,clustering,materials,homogenization,modeling
Classifier: Development Status :: 5 - Production/Stable
Classifier: Intended Audience :: Science/Research
Classifier: Topic :: Scientific/Engineering
Classifier: Topic :: Scientific/Engineering :: Artificial Intelligence
Classifier: Topic :: Scientific/Engineering :: Physics
Classifier: License :: OSI Approved :: BSD License
Classifier: Natural Language :: English
Classifier: Programming Language :: Python :: 3
Requires-Python: >=3.8
Requires-Dist: anytree==2.8.0
Requires-Dist: colorama==0.4.6
Requires-Dist: numpy==1.23.3
Requires-Dist: scikit_learn==1.2.2
Requires-Dist: scipy==1.10.0
Requires-Dist: sphinx_rtd_theme==1.2.0
Requires-Dist: sphinx-autodoc-typehints==1.22
